<import src="../template/template"></import>
<!--应邀确认-->
<view class="invited">
  <view class="title">{{ orderInfo.package_name }}</view>
  <!--时间-->
  <view class="text-wrap">
    <view class="name-l">时间:</view>
    <view class="name-r">{{ orderInfo.time }}</view>
  </view>
  <!--地址-->
  <view class="text-wrap">
    <view class="name-l">地址:</view>
    <view class="name-r">{{ orderInfo.address }}</view>
  </view>
  <!--约会对象-->
  <view class="text-wrap">
    <view class="name-l">约会对象:</view>
    <view class="name-r">{{ orderInfo.user_nicename }}</view>
  </view>
  <!--费用-->
  <view class="text-wrap">
    <view class="name-l">费用:</view>
    <view class="name-r redcolor">￥{{ orderInfo.money }}</view>
  </view>
  <!--手机-->
  <view class="text-wrap lxnumber">
    <view class="name-l">联系手机:</view>
    <view class="name-r company gender">
      <input bindinput="phoneNumberIn" type="number" maxlength="11" placeholder-class="placeholdercss" placeholder='请填写本人手机号码'/>
    </view>
  </view>
  <!--意向。。。-->
  <view class="bottom-text">
    <view>
      *意向应邀是指在缴纳意向保证金100元的前提下，可以选择任意约会对象进行应邀，最快回复的意向对象为最终约会对象，其余意向邀约自动作废，并以此为准支付费用。
    </view>
    <view>
      *在约会开始前三小时，仍未约会成功，费用将全额退回至个人余额账户。
    </view>
  </view>
  <!--confirm-->
  <view catchtap="confirmInvited" class="invitedconfirm">意向应邀</view>
  <!--意向金弹窗-->
  <view wx:if="{{ (moneyshow && payYx) }}" class="mask">
    <view class="mask-wrap">
      <view class="ts">提示</view>
      <view class="ts-two">
        您尚未支付意向金
      </view>
      <view catchtap="delMask" class="mask-confirm">
        立即支付
      </view>
    </view>
  </view>
  <!--个人资料完善弹窗-->
  <template is="finishUserData" data="{{ datashow: datashows }}"></template>
</view>

<view wx:if="{{ datingSuccess }}" class="success-mask">
<image class="success-img" src="../../images/dating-success.png"></image>
<view class="success-text">意向应邀成功，请等待通知</view>
<!--请关注“约会日”公众号，及时接收动态通知。-->
<view class="success-tips">请关注“<text>约会日</text>”公众号,及时接收动态通知。</view>
<image class="erweima" src="../../images/erweima.jpg"></image>
<view class="erweima-text">截屏保存二维码，使用微信扫一扫</view>
<!--<view class="mask-wrap">-->
  <!--<view class="mask-title sc">-->
    <!--发起邀约成功，请搜索“约会日”关注公众号，否则不能及时接收动态通知-->
  <!--</view>-->
  <!--<view catchtap="goShare" class="mask-confirm">-->
    <!--确认-->
  <!--</view>-->
<!--</view>-->
</view>